thonbol/__init__.py
thonbol/_people.py
thonbol/_version.py
thonbol_bangalex-0.0.3.dist-info/LICENSE
thonbol_bangalex-0.0.3.dist-info/METADATA
thonbol_bangalex-0.0.3.dist-info/WHEEL
thonbol_bangalex-0.0.3.dist-info/top_level.txt
thonbol_bangalex-0.0.3.dist-info/RECORD
