Metadata-Version: 2.1
Name: thonbol-bangalex
Version: 0.0.3
Summary: Thonbol for data bol (Fake Data)
Home-page: https://pypi.org/project/thonbol-bangalex/
Author: Bang Alex
Author-email: bangalex.bee@gmail.com
License: UNKNOWN
Download-URL: https://pypi.python.org/packages/source/m/thonbol-bangalex/thonbol-bangalex-0.0.3.tar.gz
Platform: UNKNOWN
Classifier: Programming Language :: Python :: 3
Classifier: License :: OSI Approved :: MIT License
Classifier: Operating System :: OS Independent
Requires-Python: >=3.6
